hypha_rpc/VERSION
hypha_rpc/__init__.py
hypha_rpc/http_client.py
hypha_rpc/pyodide_sse.py
hypha_rpc/pyodide_websocket.py
hypha_rpc/rpc.py
hypha_rpc/sync.py
hypha_rpc/webrtc_client.py
hypha_rpc/websocket_client.py
hypha_rpc/utils/__init__.py
hypha_rpc/utils/launch.py
hypha_rpc/utils/mcp.py
hypha_rpc/utils/pydantic.py
hypha_rpc/utils/schema.py
hypha_rpc/utils/serve.py
hypha_rpc-0.20.93.dist-info/METADATA
hypha_rpc-0.20.93.dist-info/WHEEL
hypha_rpc-0.20.93.dist-info/top_level.txt
hypha_rpc-0.20.93.dist-info/RECORD
